aio_intex_spa/__init__.py
aio_intex_spa/intex_spa.py
aio_intex_spa/intex_spa_exceptions.py
aio_intex_spa/intex_spa_network_layer.py
aio_intex_spa/intex_spa_object_info.py
aio_intex_spa/intex_spa_object_status.py
aio_intex_spa/intex_spa_query.py
tests/__init__.py
tests/test_intex_spa_query_checksum.py
tests/test_intex_spa_status.py
aio_intex_spa-0.9.1.dist-info/LICENSE
aio_intex_spa-0.9.1.dist-info/METADATA
aio_intex_spa-0.9.1.dist-info/WHEEL
aio_intex_spa-0.9.1.dist-info/top_level.txt
aio_intex_spa-0.9.1.dist-info/RECORD
