Metadata-Version: 2.1
Name: aio-intex-spa
Version: 0.9.1
Summary: Python client for Intex Spa wifi interface
Home-page: https://github.com/mathieu-mp/aio-intex-spa
Author: Mathieu Payrol
Author-email: aio-intex-spa@payrol.fr
Classifier: Programming Language :: Python :: 3
Classifier: License :: OSI Approved :: MIT License
Classifier: Operating System :: OS Independent
License-File: LICENSE
